{
	"_type": "export",
	"__export_format": 3,
	"__export_date": "2018-12-12T21:06:08.375Z",
	"__export_source": "insomnia.desktop.app:v6.2.3",
	"resources": [
		{
			"_id": "wrk_4e235b8f76e84a839b58f142a1ddb67e",
			"created": 1542131091220,
			"description": "",
			"modified": 1542131091220,
			"name": "facebook-api",
			"parentId": null,
			"_type": "workspace"
		},
		{
			"_id": "env_eed1d63cf3ac43ea90b575c5326654e0",
			"color": null,
			"created": 1542131091337,
			"data": {
				"base_url": "localhost:3000/api",
				"token": "eyJhbGciOiJIUzI1NiIsInR5cCI6IkpXVCJ9.eyJpZCI6IjVjMTE2OWVkMmIxMGU5MDQ5Mjk3NWJkMiIsImlhdCI6MTU0NDY0NTEwMiwiZXhwIjoxNTQ0NzMxNTAyfQ.ZiQQYNHXLp972oeFdHVR1LvdVCT3DmpX_hObhBa6e1Q",
				"token2": "eyJhbGciOiJIUzI1NiIsInR5cCI6IkpXVCJ9.eyJpZCI6IjVjMTE2YTEyMmIxMGU5MDQ5Mjk3NWJkMyIsImlhdCI6MTU0NDY0NTEzOCwiZXhwIjoxNTQ0NzMxNTM4fQ.qpRoNIJOMbmHqva-pJuLoJmfOtQdaH_m3Ul8lBY9NIk"
			},
			"isPrivate": false,
			"metaSortKey": 1542131091338,
			"modified": 1544645156061,
			"name": "New Environment",
			"parentId": "wrk_4e235b8f76e84a839b58f142a1ddb67e",
			"_type": "environment"
		},
		{
			"_id": "jar_74b9d2eade47498685f96b3b80aa08ce",
			"cookies": [],
			"created": 1542131091341,
			"modified": 1542131091341,
			"name": "Default Jar",
			"parentId": "wrk_4e235b8f76e84a839b58f142a1ddb67e",
			"_type": "cookie_jar"
		},
		{
			"_id": "fld_2bdf4f45c44b455582d8a84db2340576",
			"created": 1542194707803,
			"description": "",
			"environment": {},
			"metaSortKey": -1542194707883.75,
			"modified": 1544020118059,
			"name": "auth",
			"parentId": "wrk_4e235b8f76e84a839b58f142a1ddb67e",
			"_type": "request_group"
		},
		{
			"_id": "fld_31f8d339aa6d40ee85de99e76e0ae165",
			"created": 1544015429012,
			"description": "",
			"environment": {},
			"metaSortKey": -1542194707908.75,
			"modified": 1544015441019,
			"name": "posts",
			"parentId": "wrk_4e235b8f76e84a839b58f142a1ddb67e",
			"_type": "request_group"
		},
		{
			"_id": "fld_1772aa3bacc442c98b9fff34a68105e3",
			"created": 1544018498658,
			"description": "",
			"environment": {},
			"metaSortKey": -1542194707896.25,
			"modified": 1544018511380,
			"name": "comment",
			"parentId": "wrk_4e235b8f76e84a839b58f142a1ddb67e",
			"_type": "request_group"
		},
		{
			"_id": "fld_25de969449e0416d99b124ca9e478ebd",
			"created": 1544645195025,
			"description": "",
			"environment": {},
			"metaSortKey": -1541983894583.875,
			"modified": 1544645202007,
			"name": "users",
			"parentId": "wrk_4e235b8f76e84a839b58f142a1ddb67e",
			"_type": "request_group"
		},
		{
			"_id": "fld_f67f0a45ef7145de96d7244a17a18fa5",
			"created": 1544648710034,
			"description": "",
			"environment": {},
			"metaSortKey": -1544648710034,
			"modified": 1544648710034,
			"name": "friends",
			"parentId": "wrk_4e235b8f76e84a839b58f142a1ddb67e",
			"_type": "request_group"
		},
		{
			"_id": "req_bbb4f26f7a904e538896c782dbf3bf71",
			"authentication": {
				"prefix": "",
				"token": "{{token}}",
				"type": "bearer"
			},
			"body": {},
			"created": 1542131114633,
			"description": "",
			"headers": [],
			"isPrivate": false,
			"metaSortKey": -1542194707933.75,
			"method": "GET",
			"modified": 1544015242054,
			"name": "status",
			"parameters": [],
			"parentId": "wrk_4e235b8f76e84a839b58f142a1ddb67e",
			"settingDisableRenderRequestBody": false,
			"settingEncodeUrl": true,
			"settingMaxTimelineDataSize": 1000,
			"settingRebuildPath": true,
			"settingSendCookies": true,
			"settingStoreCookies": true,
			"url": "{{base_url}}/status",
			"_type": "request"
		},
		{
			"_id": "req_15f6b1d4c69247e08786702cdf1f5dd3",
			"authentication": {},
			"body": {
				"mimeType": "application/json",
				"text": "{\n\t\"email\": \"sheila@teste.com\",\n\t\"name\": \"sheila\",\n\t\"password\": \"teste123\",\n\t\"confirmPassword\": \"teste123\"\n}"
			},
			"created": 1542194757135,
			"description": "",
			"headers": [
				{
					"id": "pair_a4ce5dfae707439c82400c2105ce9b65",
					"name": "Content-Type",
					"value": "application/json"
				}
			],
			"isPrivate": false,
			"metaSortKey": -1542194757135,
			"method": "POST",
			"modified": 1544648490099,
			"name": "signup",
			"parameters": [],
			"parentId": "fld_2bdf4f45c44b455582d8a84db2340576",
			"settingDisableRenderRequestBody": false,
			"settingEncodeUrl": true,
			"settingMaxTimelineDataSize": 1000,
			"settingRebuildPath": true,
			"settingSendCookies": true,
			"settingStoreCookies": true,
			"url": "{{base_url}}/signup",
			"_type": "request"
		},
		{
			"_id": "req_46caed242d4b439abdc9adcd3539fcfb",
			"authentication": {},
			"body": {
				"mimeType": "application/json",
				"text": "{\n\t\"email\": \"sheila@teste.com\",\n\t\"password\":\"teste123\"\n}"
			},
			"created": 1542205651689,
			"description": "",
			"headers": [
				{
					"id": "pair_a4ce5dfae707439c82400c2105ce9b65",
					"name": "Content-Type",
					"value": "application/json"
				}
			],
			"isPrivate": false,
			"metaSortKey": -1542194732534.375,
			"method": "POST",
			"modified": 1544648690718,
			"name": "signin",
			"parameters": [],
			"parentId": "fld_2bdf4f45c44b455582d8a84db2340576",
			"settingDisableRenderRequestBody": false,
			"settingEncodeUrl": true,
			"settingMaxTimelineDataSize": 1000,
			"settingRebuildPath": true,
			"settingSendCookies": true,
			"settingStoreCookies": true,
			"url": "{{base_url}}/signin",
			"_type": "request"
		},
		{
			"_id": "req_d3222c1bd3b1497b88b1dde62d0fe426",
			"authentication": {
				"prefix": "",
				"token": "{{ token2 }}",
				"type": "bearer"
			},
			"body": {
				"mimeType": "application/json",
				"text": "{\n\t\"content\": \"meu primeiro post\"\n}"
			},
			"created": 1544015436117,
			"description": "",
			"headers": [
				{
					"id": "pair_a4ce5dfae707439c82400c2105ce9b65",
					"name": "Content-Type",
					"value": "application/json"
				},
				{
					"id": "pair_9048dbcd2187440cbdd916ecbafa2b7f",
					"name": "",
					"value": ""
				}
			],
			"isPrivate": false,
			"metaSortKey": -1542194720234.0625,
			"method": "POST",
			"modified": 1544647235120,
			"name": "create",
			"parameters": [],
			"parentId": "fld_31f8d339aa6d40ee85de99e76e0ae165",
			"settingDisableRenderRequestBody": false,
			"settingEncodeUrl": true,
			"settingMaxTimelineDataSize": 1000,
			"settingRebuildPath": true,
			"settingSendCookies": true,
			"settingStoreCookies": true,
			"url": "{{base_url}}/posts",
			"_type": "request"
		},
		{
			"_id": "req_174a15ec526a48fe9dfe82a8bed53e08",
			"authentication": {
				"prefix": "",
				"token": "{{token}}",
				"type": "bearer"
			},
			"body": {
				"mimeType": "application/json",
				"text": "{\n\t\"content\": \"meu primeiro post\"\n}"
			},
			"created": 1544016049863,
			"description": "",
			"headers": [
				{
					"id": "pair_a4ce5dfae707439c82400c2105ce9b65",
					"name": "Content-Type",
					"value": "application/json"
				},
				{
					"id": "pair_9048dbcd2187440cbdd916ecbafa2b7f",
					"name": "",
					"value": ""
				}
			],
			"isPrivate": false,
			"metaSortKey": -1542194714083.9062,
			"method": "GET",
			"modified": 1544642326353,
			"name": "show",
			"parameters": [],
			"parentId": "fld_31f8d339aa6d40ee85de99e76e0ae165",
			"settingDisableRenderRequestBody": false,
			"settingEncodeUrl": true,
			"settingMaxTimelineDataSize": 1000,
			"settingRebuildPath": true,
			"settingSendCookies": true,
			"settingStoreCookies": true,
			"url": "{{base_url}}/posts/5c07cfeaaac50f00d16449d8",
			"_type": "request"
		},
		{
			"_id": "req_cae4e60c850045db993c2394acee7946",
			"authentication": {
				"prefix": "",
				"token": "{{token}}",
				"type": "bearer"
			},
			"body": {
				"mimeType": "application/json",
				"text": ""
			},
			"created": 1544017246264,
			"description": "",
			"headers": [
				{
					"id": "pair_a4ce5dfae707439c82400c2105ce9b65",
					"name": "Content-Type",
					"value": "application/json"
				},
				{
					"id": "pair_9048dbcd2187440cbdd916ecbafa2b7f",
					"name": "",
					"value": ""
				}
			],
			"isPrivate": false,
			"metaSortKey": -1542194717158.9844,
			"method": "POST",
			"modified": 1544647921428,
			"name": "like",
			"parameters": [],
			"parentId": "fld_31f8d339aa6d40ee85de99e76e0ae165",
			"settingDisableRenderRequestBody": false,
			"settingEncodeUrl": true,
			"settingMaxTimelineDataSize": 1000,
			"settingRebuildPath": true,
			"settingSendCookies": true,
			"settingStoreCookies": true,
			"url": "{{base_url}}/posts/5c117237602c4d0656b456a7/like",
			"_type": "request"
		},
		{
			"_id": "req_fdbd785fe9484604b084d81f09fdefff",
			"authentication": {
				"prefix": "",
				"token": "{{token}}",
				"type": "bearer"
			},
			"body": {
				"mimeType": "application/json",
				"text": ""
			},
			"created": 1544021974129,
			"description": "",
			"headers": [
				{
					"id": "pair_a4ce5dfae707439c82400c2105ce9b65",
					"name": "Content-Type",
					"value": "application/json"
				},
				{
					"id": "pair_9048dbcd2187440cbdd916ecbafa2b7f",
					"name": "",
					"value": ""
				}
			],
			"isPrivate": false,
			"metaSortKey": -1542194718696.5234,
			"method": "DELETE",
			"modified": 1544022009436,
			"name": "destroy",
			"parameters": [],
			"parentId": "fld_31f8d339aa6d40ee85de99e76e0ae165",
			"settingDisableRenderRequestBody": false,
			"settingEncodeUrl": true,
			"settingMaxTimelineDataSize": 1000,
			"settingRebuildPath": true,
			"settingSendCookies": true,
			"settingStoreCookies": true,
			"url": "{{base_url}}/posts/5c07e7f2edb5b5066bd65d0d",
			"_type": "request"
		},
		{
			"_id": "req_1e64451ec9c6439ea7f199a2886b87fb",
			"authentication": {
				"prefix": "",
				"token": "{{token}}",
				"type": "bearer"
			},
			"body": {
				"mimeType": "application/json",
				"text": "{\n\t\"content\": \"meu quarto comentário\"\n}"
			},
			"created": 1544018498684,
			"description": "",
			"headers": [
				{
					"id": "pair_a4ce5dfae707439c82400c2105ce9b65",
					"name": "Content-Type",
					"value": "application/json"
				},
				{
					"id": "pair_9048dbcd2187440cbdd916ecbafa2b7f",
					"name": "",
					"value": ""
				}
			],
			"isPrivate": false,
			"metaSortKey": -1542194720234.0625,
			"method": "POST",
			"modified": 1544022876108,
			"name": "create",
			"parameters": [],
			"parentId": "fld_1772aa3bacc442c98b9fff34a68105e3",
			"settingDisableRenderRequestBody": false,
			"settingEncodeUrl": true,
			"settingMaxTimelineDataSize": 1000,
			"settingRebuildPath": true,
			"settingSendCookies": true,
			"settingStoreCookies": true,
			"url": "{{base_url}}/posts/5c07cfeaaac50f00d16449d8/comments",
			"_type": "request"
		},
		{
			"_id": "req_99ada7c327a640238ed57626f24eb650",
			"authentication": {
				"prefix": "",
				"token": "{{token}}",
				"type": "bearer"
			},
			"body": {
				"mimeType": "application/json",
				"text": "{\n\t\"content\": \"meu primeiro post\"\n}"
			},
			"created": 1544018498706,
			"description": "",
			"headers": [
				{
					"id": "pair_a4ce5dfae707439c82400c2105ce9b65",
					"name": "Content-Type",
					"value": "application/json"
				},
				{
					"id": "pair_9048dbcd2187440cbdd916ecbafa2b7f",
					"name": "",
					"value": ""
				}
			],
			"isPrivate": false,
			"metaSortKey": -1542194714083.9062,
			"method": "GET",
			"modified": 1544645168694,
			"name": "show",
			"parameters": [],
			"parentId": "fld_1772aa3bacc442c98b9fff34a68105e3",
			"settingDisableRenderRequestBody": false,
			"settingEncodeUrl": true,
			"settingMaxTimelineDataSize": 1000,
			"settingRebuildPath": true,
			"settingSendCookies": true,
			"settingStoreCookies": true,
			"url": "{{base_url}}/posts/5c07cfeaaac50f00d16449d8/comments/5c07dabf39d3010443d3e217",
			"_type": "request"
		},
		{
			"_id": "req_b4c03d70887e4dbd93208668246ccf71",
			"authentication": {
				"prefix": "",
				"token": "{{token}}",
				"type": "bearer"
			},
			"body": {
				"mimeType": "application/json",
				"text": ""
			},
			"created": 1544018498711,
			"description": "",
			"headers": [
				{
					"id": "pair_a4ce5dfae707439c82400c2105ce9b65",
					"name": "Content-Type",
					"value": "application/json"
				},
				{
					"id": "pair_9048dbcd2187440cbdd916ecbafa2b7f",
					"name": "",
					"value": ""
				}
			],
			"isPrivate": false,
			"metaSortKey": -1542194717158.9844,
			"method": "POST",
			"modified": 1544020025476,
			"name": "like",
			"parameters": [],
			"parentId": "fld_1772aa3bacc442c98b9fff34a68105e3",
			"settingDisableRenderRequestBody": false,
			"settingEncodeUrl": true,
			"settingMaxTimelineDataSize": 1000,
			"settingRebuildPath": true,
			"settingSendCookies": true,
			"settingStoreCookies": true,
			"url": "{{base_url}}/posts/5c07cfeaaac50f00d16449d8/comments/5c07dabf39d3010443d3e217/like",
			"_type": "request"
		},
		{
			"_id": "req_46be865ed181447ba4dae49e67d4d4fb",
			"authentication": {
				"prefix": "",
				"token": "{{token}}",
				"type": "bearer"
			},
			"body": {
				"mimeType": "application/json",
				"text": ""
			},
			"created": 1544022416062,
			"description": "",
			"headers": [
				{
					"id": "pair_a4ce5dfae707439c82400c2105ce9b65",
					"name": "Content-Type",
					"value": "application/json"
				},
				{
					"id": "pair_9048dbcd2187440cbdd916ecbafa2b7f",
					"name": "",
					"value": ""
				}
			],
			"isPrivate": false,
			"metaSortKey": -1542194719465.293,
			"method": "DELETE",
			"modified": 1544022882139,
			"name": "destroy",
			"parameters": [],
			"parentId": "fld_1772aa3bacc442c98b9fff34a68105e3",
			"settingDisableRenderRequestBody": false,
			"settingEncodeUrl": true,
			"settingMaxTimelineDataSize": 1000,
			"settingRebuildPath": true,
			"settingSendCookies": true,
			"settingStoreCookies": true,
			"url": "{{base_url}}/posts/5c07cfeaaac50f00d16449d8/comments/5c07eb5be2059d0773fc0b00",
			"_type": "request"
		},
		{
			"_id": "req_a0d34297a0f64a549f5f53198971ebe7",
			"authentication": {
				"token": "{{token}}",
				"type": "bearer"
			},
			"body": {
				"mimeType": "application/json",
				"text": ""
			},
			"created": 1544645195029,
			"description": "",
			"headers": [
				{
					"id": "pair_a4ce5dfae707439c82400c2105ce9b65",
					"name": "Content-Type",
					"value": "application/json"
				}
			],
			"isPrivate": false,
			"metaSortKey": -1542194757135,
			"method": "GET",
			"modified": 1544648019347,
			"name": "show",
			"parameters": [],
			"parentId": "fld_25de969449e0416d99b124ca9e478ebd",
			"settingDisableRenderRequestBody": false,
			"settingEncodeUrl": true,
			"settingMaxTimelineDataSize": 1000,
			"settingRebuildPath": true,
			"settingSendCookies": true,
			"settingStoreCookies": true,
			"url": "{{base_url}}/users/5c116a122b10e90492975bd3",
			"_type": "request"
		},
		{
			"_id": "req_ace49d0ac4034e0e9e53744e5facfc50",
			"authentication": {
				"token": "{{token}}",
				"type": "bearer"
			},
			"body": {
				"mimeType": "application/json",
				"text": ""
			},
			"created": 1544645471312,
			"description": "",
			"headers": [
				{
					"id": "pair_a4ce5dfae707439c82400c2105ce9b65",
					"name": "Content-Type",
					"value": "application/json"
				}
			],
			"isPrivate": false,
			"metaSortKey": -1542194750984.8438,
			"method": "GET",
			"modified": 1544648022041,
			"name": "self",
			"parameters": [],
			"parentId": "fld_25de969449e0416d99b124ca9e478ebd",
			"settingDisableRenderRequestBody": false,
			"settingEncodeUrl": true,
			"settingMaxTimelineDataSize": 1000,
			"settingRebuildPath": true,
			"settingSendCookies": true,
			"settingStoreCookies": true,
			"url": "{{base_url}}/users/self",
			"_type": "request"
		},
		{
			"_id": "req_973cad23efd945acbebc38df2d51e001",
			"authentication": {
				"prefix": "",
				"token": "{{token}}",
				"type": "bearer"
			},
			"body": {
				"mimeType": "application/json",
				"text": ""
			},
			"created": 1544647862368,
			"description": "",
			"headers": [
				{
					"id": "pair_a4ce5dfae707439c82400c2105ce9b65",
					"name": "Content-Type",
					"value": "application/json"
				}
			],
			"isPrivate": false,
			"metaSortKey": -1542194754059.9219,
			"method": "GET",
			"modified": 1544647924398,
			"name": "feed",
			"parameters": [],
			"parentId": "fld_25de969449e0416d99b124ca9e478ebd",
			"settingDisableRenderRequestBody": false,
			"settingEncodeUrl": true,
			"settingMaxTimelineDataSize": 1000,
			"settingRebuildPath": true,
			"settingSendCookies": true,
			"settingStoreCookies": true,
			"url": "{{base_url}}/users/feed",
			"_type": "request"
		},
		{
			"_id": "req_7697a5f67bb74ba1bafe3e3ada848804",
			"authentication": {
				"token": "{{token}}",
				"type": "bearer"
			},
			"body": {
				"mimeType": "application/json",
				"text": "{\n\t\"name\": \"murilex\",\n\t\"password\": \"teste1234\",\n\t\"confirmPassword\": \"teste1234\"\n}"
			},
			"created": 1544648025652,
			"description": "",
			"headers": [
				{
					"id": "pair_a4ce5dfae707439c82400c2105ce9b65",
					"name": "Content-Type",
					"value": "application/json"
				}
			],
			"isPrivate": false,
			"metaSortKey": -1542194747909.7656,
			"method": "GET",
			"modified": 1544648660721,
			"name": "update",
			"parameters": [],
			"parentId": "fld_25de969449e0416d99b124ca9e478ebd",
			"settingDisableRenderRequestBody": false,
			"settingEncodeUrl": true,
			"settingMaxTimelineDataSize": 1000,
			"settingRebuildPath": true,
			"settingSendCookies": true,
			"settingStoreCookies": true,
			"url": "{{base_url}}/users/self/update",
			"_type": "request"
		},
		{
			"_id": "req_5d6bcdb414ec4b769c2bad8a6b476f91",
			"authentication": {
				"token": "{{token}}",
				"type": "bearer"
			},
			"body": {
				"mimeType": "application/json",
				"text": ""
			},
			"created": 1544645358830,
			"description": "",
			"headers": [
				{
					"id": "pair_a4ce5dfae707439c82400c2105ce9b65",
					"name": "Content-Type",
					"value": "application/json"
				}
			],
			"isPrivate": false,
			"metaSortKey": -1542194738834.5312,
			"method": "POST",
			"modified": 1544648727174,
			"name": "friendship",
			"parameters": [],
			"parentId": "fld_f67f0a45ef7145de96d7244a17a18fa5",
			"settingDisableRenderRequestBody": false,
			"settingEncodeUrl": true,
			"settingMaxTimelineDataSize": 1000,
			"settingRebuildPath": true,
			"settingSendCookies": true,
			"settingStoreCookies": true,
			"url": "{{base_url}}/users/5c116a122b10e90492975bd3/friendship",
			"_type": "request"
		},
		{
			"_id": "req_a87ad8230f31483eb01dab3065ea902e",
			"authentication": {
				"token": "{{token}}",
				"type": "bearer"
			},
			"body": {
				"mimeType": "application/json",
				"text": ""
			},
			"created": 1544645733574,
			"description": "",
			"headers": [
				{
					"id": "pair_a4ce5dfae707439c82400c2105ce9b65",
					"name": "Content-Type",
					"value": "application/json"
				}
			],
			"isPrivate": false,
			"metaSortKey": -1542194738784.5312,
			"method": "DELETE",
			"modified": 1544648725843,
			"name": "friendship",
			"parameters": [],
			"parentId": "fld_f67f0a45ef7145de96d7244a17a18fa5",
			"settingDisableRenderRequestBody": false,
			"settingEncodeUrl": true,
			"settingMaxTimelineDataSize": 1000,
			"settingRebuildPath": true,
			"settingSendCookies": true,
			"settingStoreCookies": true,
			"url": "{{base_url}}/users/5c116a122b10e90492975bd3/friendship",
			"_type": "request"
		}
	]
}